azqueuetweeter/__init__.py
azqueuetweeter/storage.py
azqueuetweeter/twitter.py
azqueuetweeter-0.1.1.dist-info/LICENSE.md
azqueuetweeter-0.1.1.dist-info/WHEEL
azqueuetweeter-0.1.1.dist-info/METADATA
azqueuetweeter-0.1.1.dist-info/RECORD
