Metadata-Version: 2.1
Name: azqueuetweeter
Version: 0.1.1
Summary: Tweet from Azure Storage Queues
License: MIT
Author: Jay Miller
Author-email: kjaymiller@gmail.com
Requires-Python: >=3.8.14,<4.0.0
Classifier: License :: OSI Approved :: MIT License
Classifier: Programming Language :: Python :: 3
Classifier: Programming Language :: Python :: 3.9
Classifier: Programming Language :: Python :: 3.10
Requires-Dist: azure-storage-queue (>=12.4.0,<13.0.0)
Requires-Dist: tweepy (>=4.10.1,<5.0.0)
